f4ratk/__init__.py
f4ratk/__main__.py
f4ratk/analyze/__init__.py
f4ratk/analyze/analyze.py
f4ratk/analyze/api.py
f4ratk/analyze/evaluation.py
f4ratk/analyze/regression.py
f4ratk/cli/__init__.py
f4ratk/cli/commands.py
f4ratk/cli/output.py
f4ratk/cli/types.py
f4ratk/converter.py
f4ratk/cost.py
f4ratk/data_reader.py
f4ratk/directories.py
f4ratk/domain.py
f4ratk/exchange.py
f4ratk/fama.py
f4ratk/file/__init__.py
f4ratk/file/analyze.py
f4ratk/file/api.py
f4ratk/file/reader.py
f4ratk/history.py
f4ratk/infrastructure.py
f4ratk/portfolio/__init__.py
f4ratk/portfolio/analyze.py
f4ratk/portfolio/api.py
f4ratk/portfolio/ports.py
f4ratk/portfolio/reader/__init__.py
f4ratk/portfolio/reader/api.py
f4ratk/portfolio/reader/nodes.py
f4ratk/portfolio/reader/reader.py
f4ratk/shared.py
f4ratk/ticker/__init__.py
f4ratk/ticker/analyze.py
f4ratk/ticker/api.py
f4ratk/ticker/reader.py
f4ratk/web/__init__.py
f4ratk/web/__main__.py
f4ratk/web/controller.py
f4ratk/web/cost/__init__.py
f4ratk/web/cost/controller.py
f4ratk/web/infrastructure.py
f4ratk/web/mail/__init__.py
f4ratk/web/mail/controller.py
f4ratk/web/mail/mail.py
f4ratk/web/server.py
f4ratk-2023.1.dist-info/COPYING
f4ratk-2023.1.dist-info/LICENSE
f4ratk-2023.1.dist-info/METADATA
f4ratk-2023.1.dist-info/WHEEL
f4ratk-2023.1.dist-info/entry_points.txt
f4ratk-2023.1.dist-info/RECORD
